test/__init__.py
test/num2word.py
test0707-0.1.0.dist-info/LICENSE
test0707-0.1.0.dist-info/METADATA
test0707-0.1.0.dist-info/WHEEL
test0707-0.1.0.dist-info/top_level.txt
test0707-0.1.0.dist-info/RECORD
